computer_use_ootb/.gitignore
computer_use_ootb/LICENSE
computer_use_ootb/README.md
computer_use_ootb/__init__.py
computer_use_ootb/app.py
computer_use_ootb/dev-requirements.txt
computer_use_ootb/assets/Teaser.gif
computer_use_ootb/assets/gradio_interface.png
computer_use_ootb/assets/ootb_icon.png
computer_use_ootb/assets/ootb_logo.png
computer_use_ootb/assets/wechat_3.jpg
computer_use_ootb/assets/examples/ootb_examples.json
computer_use_ootb/assets/examples/init_states/amazon.png
computer_use_ootb/assets/examples/init_states/booking.png
computer_use_ootb/assets/examples/init_states/honkai_star_rail.png
computer_use_ootb/assets/examples/init_states/honkai_star_rail_showui.png
computer_use_ootb/assets/examples/init_states/ign.png
computer_use_ootb/assets/examples/init_states/powerpoint.png
computer_use_ootb/assets/examples/init_states/powerpoint_homepage.png
computer_use_ootb/computer_use_demo/__init__.py
computer_use_ootb/computer_use_demo/loop.py
computer_use_ootb/computer_use_demo/executor/__init__.py
computer_use_ootb/computer_use_demo/executor/anthropic_executor.py
computer_use_ootb/computer_use_demo/executor/showui_executor.py
computer_use_ootb/computer_use_demo/gui_agent/__init__.py
computer_use_ootb/computer_use_demo/gui_agent/anthropic_agent.py
computer_use_ootb/computer_use_demo/gui_agent/showui_agent.py
computer_use_ootb/computer_use_demo/gui_agent/llm_utils/__init__.py
computer_use_ootb/computer_use_demo/gui_agent/llm_utils/llm_utils.py
computer_use_ootb/computer_use_demo/gui_agent/llm_utils/oai.py
computer_use_ootb/computer_use_demo/gui_agent/llm_utils/qwen.py
computer_use_ootb/computer_use_demo/gui_agent/llm_utils/run_llm.py
computer_use_ootb/computer_use_demo/gui_agent/planner/__init__.py
computer_use_ootb/computer_use_demo/gui_agent/planner/api_vlm_planner.py
computer_use_ootb/computer_use_demo/gui_agent/planner/local_vlm_planner.py
computer_use_ootb/computer_use_demo/tools/__init__.py
computer_use_ootb/computer_use_demo/tools/base.py
computer_use_ootb-0.0.5.dist-info/METADATA
computer_use_ootb-0.0.5.dist-info/WHEEL
computer_use_ootb-0.0.5.dist-info/entry_points.txt
computer_use_ootb-0.0.5.dist-info/RECORD
