Metadata-Version: 2.4
Name: computer-use-ootb
Version: 0.0.5
Summary: Computer Use OOTB
Author-email: Siyuan Hu <siyuan.hu.sg@gmail.com>
Requires-Python: >=3.12
Requires-Dist: aiofiles>=23.2.1
Requires-Dist: annotated-types>=0.7.0
Requires-Dist: anthropic>=0.45.0
Requires-Dist: anyio>=4.8.0
Requires-Dist: certifi>=2024.12.14
Requires-Dist: charset-normalizer>=3.4.1
Requires-Dist: click>=8.1.8
Requires-Dist: cython>=3.0.11
Requires-Dist: dashscope>=1.22.1
Requires-Dist: distro>=1.9.0
Requires-Dist: fastapi>=0.115.7
Requires-Dist: ffmpy>=0.5.0
Requires-Dist: filelock>=3.17.0
Requires-Dist: fsspec>=2024.12.0
Requires-Dist: gradio-client>=1.6.0
Requires-Dist: gradio>=5.13.1
Requires-Dist: h11>=0.14.0
Requires-Dist: httpcore>=1.0.7
Requires-Dist: httpx>=0.28.1
Requires-Dist: huggingface-hub>=0.27.1
Requires-Dist: idna>=3.10
Requires-Dist: jinja2>=3.1.5
Requires-Dist: jiter>=0.8.2
Requires-Dist: markdown-it-py>=3.0.0
Requires-Dist: markupsafe>=2.1.5
Requires-Dist: mdurl>=0.1.2
Requires-Dist: mpmath>=1.3.0
Requires-Dist: networkx>=3.4.2
Requires-Dist: numpy>=2.2.2
Requires-Dist: orjson>=3.10.15
Requires-Dist: packaging>=24.2
Requires-Dist: pandas>=2.2.3
Requires-Dist: pillow>=11.1.0
Requires-Dist: pyautogui>=0.9.54
Requires-Dist: pydantic-core>=2.27.2
Requires-Dist: pydantic>=2.10.6
Requires-Dist: pydub>=0.25.1
Requires-Dist: pygments>=2.19.1
Requires-Dist: pyobjc-core>=11.0
Requires-Dist: pyobjc-framework-cocoa>=11.0
Requires-Dist: python-dateutil>=2.9.0.post0
Requires-Dist: python-multipart>=0.0.20
Requires-Dist: pytz>=2024.2
Requires-Dist: pyyaml>=6.0.2
Requires-Dist: qwen-vl-utils>=0.0.9
Requires-Dist: regex>=2024.11.6
Requires-Dist: requests>=2.32.3
Requires-Dist: rich>=13.9.4
Requires-Dist: ruff>=0.9.3
Requires-Dist: safehttpx>=0.1.6
Requires-Dist: safetensors>=0.5.2
Requires-Dist: screeninfo>=0.8.1
Requires-Dist: semantic-version>=2.10.0
Requires-Dist: shellingham>=1.5.4
Requires-Dist: six>=1.17.0
Requires-Dist: sniffio>=1.3.1
Requires-Dist: starlette>=0.45.3
Requires-Dist: sympy>=1.13.1
Requires-Dist: tokenizers>=0.21.0
Requires-Dist: tomlkit>=0.13.2
Requires-Dist: torch>=2.5.1
Requires-Dist: torchvision>=0.20.1
Requires-Dist: tqdm>=4.67.1
Requires-Dist: transformers>=4.48.1
Requires-Dist: typer>=0.15.1
Requires-Dist: typing-extensions>=4.12.2
Requires-Dist: tzdata>=2025.1
Requires-Dist: urllib3>=2.3.0
Requires-Dist: uvicorn>=0.34.0
Requires-Dist: websockets>=14.2
Provides-Extra: dev
Requires-Dist: pytest-asyncio>=0.23.6; extra == 'dev'
Requires-Dist: pytest>=8.3.3; extra == 'dev'
Requires-Dist: ruff>=0.6.7; extra == 'dev'
